{
  "annotations": {
    "list": [
      {
        "builtIn": 1,
        "datasource": "-- Grafana --",
        "enable": true,
        "hide": true,
        "iconColor": "rgba(0, 211, 255, 1)",
        "name": "Annotations & Alerts",
        "type": "dashboard"
      }
    ]
  },
  "description": "This dashboard leverages the Prometheus exporter I wrote to fetch information about GitLab CI pipelines statuses. More information here: https://github.com/mvisonneau/gitlab-ci-pipelines-exporter",
  "editable": true,
  "gnetId": 10620,
  "graphTooltip": 0,
  "iteration": 1604494963195,
  "links": [],
  "panels": [
    {
      "colors": [
        "#299c46",
        "rgba(237, 129, 40, 0.89)",
        "#d44a3a",
        "#4040a0"
      ],
      "datasource": null,
      "fieldConfig": {
        "defaults": {
          "custom": {}
        },
        "overrides": []
      },
      "gridPos": {
        "h": 5,
        "w": 16,
        "x": 0,
        "y": 0
      },
      "id": 110,
      "links": [],
      "mappingType": 1,
      "mappingTypes": [
        {
          "name": "value to text",
          "value": 1
        },
        {
          "name": "range to text",
          "value": 2
        }
      ],
      "polystat": {
        "animationSpeed": 2500,
        "columnAutoSize": true,
        "columns": "",
        "defaultClickThrough": "",
        "defaultClickThroughNewTab": false,
        "defaultClickThroughSanitize": false,
        "displayLimit": "",
        "fontAutoColor": true,
        "fontAutoScale": true,
        "fontSize": 4,
        "fontType": "Roboto",
        "globalDecimals": 2,
        "globalDisplayMode": "all",
        "globalDisplayTextTriggeredEmpty": "OK",
        "globalOperatorName": "current",
        "globalUnitFormat": "short",
        "gradientEnabled": true,
        "hexagonSortByDirection": 1,
        "hexagonSortByField": "name",
        "maxMetrics": 0,
        "polygonBorderColor": "#10111c",
        "polygonBorderSize": 1,
        "polygonGlobalFillColor": "#3274D9",
        "radius": "",
        "radiusAutoSize": true,
        "rowAutoSize": false,
        "rows": 4,
        "shape": "hexagon_pointed_top",
        "tooltipDisplayMode": "all",
        "tooltipDisplayTextTriggeredEmpty": "OK",
        "tooltipFontSize": 12,
        "tooltipFontType": "Roboto",
        "tooltipPrimarySortDirection": 2,
        "tooltipPrimarySortField": "thresholdLevel",
        "tooltipSecondarySortDirection": 2,
        "tooltipSecondarySortField": "value",
        "tooltipTimestampEnabled": false,
        "valueEnabled": false
      },
      "rangeMaps": [
        {
          "from": "null",
          "text": "N/A",
          "to": "null"
        }
      ],
      "savedComposites": [],
      "savedOverrides": [
        {
          "$$hashKey": "object:1596",
          "clickThrough": "",
          "colors": [
            "#299c46",
            "#e5ac0e",
            "#bf1b00",
            "#ffffff"
          ],
          "decimals": "",
          "enabled": true,
          "label": "OVERRIDE 1",
          "metricName": "/.*/",
          "operatorName": "current",
          "prefix": "",
          "sanitizeURLEnabled": true,
          "scaledDecimals": null,
          "suffix": "",
          "thresholds": [
            {
              "$$hashKey": "object:1610",
              "color": "#299c46",
              "state": 0,
              "value": 0
            },
            {
              "$$hashKey": "object:1611",
              "color": "#E0B400",
              "state": 3,
              "value": 1
            },
            {
              "$$hashKey": "object:1612",
              "color": "#C4162A",
              "state": 2,
              "value": 3
            }
          ],
          "unitFormat": "short"
        }
      ],
      "targets": [
        {
          "expr": "gitlab_ci_environment_behind_commits_count{project=~\"($OWNER).*\",project=~\"$PROJECT\", environment=~\"$ENVIRONMENT\"}",
          "format": "time_series",
          "hide": false,
          "instant": true,
          "interval": "",
          "intervalFactor": 1,
          "legendFormat": "                                               {{ project }} - {{ environment }}",
          "refId": "A"
        }
      ],
      "timeFrom": null,
      "timeShift": null,
      "title": "",
      "transparent": true,
      "type": "grafana-polystat-panel",
      "valueMaps": [
        {
          "op": "=",
          "text": "N/A",
          "value": "null"
        }
      ]
    },
    {
      "cacheTimeout": null,
      "datasource": null,
      "fieldConfig": {
        "defaults": {
          "custom": {},
          "decimals": 0,
          "mappings": [
            {
              "id": 0,
              "op": "=",
              "text": "N/A",
              "type": 1,
              "value": "null"
            }
          ],
          "nullValueMode": "connected",
          "thresholds": {
            "mode": "absolute",
            "steps": [
              {
                "color": "semi-dark-blue",
                "value": null
              },
              {
                "color": "#d44a3a"
              }
            ]
          },
          "unit": "none"
        },
        "overrides": []
      },
      "gridPos": {
        "h": 3,
        "w": 2,
        "x": 16,
        "y": 0
      },
      "id": 107,
      "interval": null,
      "links": [],
      "maxDataPoints": 100,
      "options": {
        "colorMode": "background",
        "fieldOptions": {
          "calcs": [
            "lastNotNull"
          ]
        },
        "graphMode": "area",
        "justifyMode": "auto",
        "orientation": "horizontal",
        "reduceOptions": {
          "calcs": [
            "last"
          ],
          "fields": "",
          "values": false
        },
        "textMode": "auto"
      },
      "pluginVersion": "7.3.1",
      "targets": [
        {
          "expr": "count(gitlab_ci_environment_information{available=\"true\", project=~\"($OWNER).*\",project=~\"$PROJECT\", environment=~\"$ENVIRONMENT\"}) or vector(0)",
          "format": "time_series",
          "instant": false,
          "interval": "",
          "intervalFactor": 1,
          "legendFormat": "",
          "refId": "A"
        }
      ],
      "timeFrom": null,
      "timeShift": null,
      "title": "AVAILABLE",
      "type": "stat"
    },
    {
      "cacheTimeout": null,
      "datasource": null,
      "fieldConfig": {
        "defaults": {
          "custom": {},
          "decimals": 0,
          "mappings": [
            {
              "id": 0,
              "op": "=",
              "text": "N/A",
              "type": 1,
              "value": "null"
            }
          ],
          "nullValueMode": "connected",
          "thresholds": {
            "mode": "absolute",
            "steps": [
              {
                "color": "#299c46",
                "value": null
              },
              {
                "color": "#C4162A",
                "value": 1
              },
              {
                "color": "#d44a3a"
              }
            ]
          },
          "unit": "none"
        },
        "overrides": []
      },
      "gridPos": {
        "h": 3,
        "w": 2,
        "x": 18,
        "y": 0
      },
      "id": 113,
      "interval": null,
      "links": [],
      "maxDataPoints": 100,
      "options": {
        "colorMode": "background",
        "fieldOptions": {
          "calcs": [
            "lastNotNull"
          ]
        },
        "graphMode": "area",
        "justifyMode": "auto",
        "orientation": "horizontal",
        "reduceOptions": {
          "calcs": [
            "last"
          ],
          "fields": "",
          "values": false
        },
        "textMode": "auto"
      },
      "pluginVersion": "7.3.1",
      "targets": [
        {
          "expr": "count(gitlab_ci_environment_behind_commits_count{project=~\"($OWNER).*\",project=~\"$PROJECT\", environment=~\"$ENVIRONMENT.*\"} > 0) or vector(0)",
          "format": "time_series",
          "instant": false,
          "interval": "",
          "intervalFactor": 1,
          "legendFormat": "",
          "refId": "A"
        }
      ],
      "timeFrom": null,
      "timeShift": null,
      "title": "NOT UP TO DATE",
      "type": "stat"
    },
    {
      "cacheTimeout": null,
      "datasource": null,
      "fieldConfig": {
        "defaults": {
          "custom": {},
          "decimals": 0,
          "mappings": [
            {
              "id": 0,
              "op": "=",
              "text": "N/A",
              "type": 1,
              "value": "null"
            }
          ],
          "nullValueMode": "connected",
          "thresholds": {
            "mode": "absolute",
            "steps": [
              {
                "color": "#299c46",
                "value": null
              },
              {
                "color": "#C4162A",
                "value": 1
              },
              {
                "color": "#d44a3a"
              }
            ]
          },
          "unit": "none"
        },
        "overrides": []
      },
      "gridPos": {
        "h": 3,
        "w": 2,
        "x": 20,
        "y": 0
      },
      "id": 111,
      "interval": null,
      "links": [],
      "maxDataPoints": 100,
      "options": {
        "colorMode": "background",
        "fieldOptions": {
          "calcs": [
            "lastNotNull"
          ]
        },
        "graphMode": "area",
        "justifyMode": "auto",
        "orientation": "horizontal",
        "reduceOptions": {
          "calcs": [
            "last"
          ],
          "fields": "",
          "values": false
        },
        "textMode": "auto"
      },
      "pluginVersion": "7.3.1",
      "targets": [
        {
          "expr": "count(gitlab_ci_environment_status{status=\"failed\", project=~\"($OWNER).*\",project=~\"$PROJECT\", environment=~\"$ENVIRONMENT\"} > 0) or vector(0)",
          "format": "time_series",
          "instant": false,
          "interval": "",
          "intervalFactor": 1,
          "legendFormat": "",
          "refId": "A"
        }
      ],
      "timeFrom": null,
      "timeShift": null,
      "title": "FAILED DEPLOYMENTS",
      "type": "stat"
    },
    {
      "datasource": null,
      "fieldConfig": {
        "defaults": {
          "custom": {}
        },
        "overrides": []
      },
      "gridPos": {
        "h": 3,
        "w": 2,
        "x": 22,
        "y": 0
      },
      "id": 118,
      "options": {
        "content": "<p style=\"text-align:center;\"><img src=\"https://about.gitlab.com/images/press/logo/png/gitlab-logo-500.png\" width=100px/></p>",
        "mode": "html"
      },
      "pluginVersion": "7.3.1",
      "timeFrom": null,
      "timeShift": null,
      "title": "",
      "transparent": true,
      "type": "text"
    },
    {
      "cacheTimeout": null,
      "datasource": "Prometheus",
      "fieldConfig": {
        "defaults": {
          "custom": {},
          "decimals": 0,
          "mappings": [
            {
              "id": 0,
              "op": "=",
              "text": "N/A",
              "type": 1,
              "value": "null"
            }
          ],
          "nullValueMode": "connected",
          "thresholds": {
            "mode": "absolute",
            "steps": [
              {
                "color": "#299c46",
                "value": null
              },
              {
                "color": "#C4162A",
                "value": 1
              },
              {
                "color": "#d44a3a"
              }
            ]
          },
          "unit": "none"
        },
        "overrides": []
      },
      "gridPos": {
        "h": 3,
        "w": 3,
        "x": 16,
        "y": 3
      },
      "id": 112,
      "interval": null,
      "links": [],
      "maxDataPoints": 100,
      "options": {
        "colorMode": "background",
        "fieldOptions": {
          "calcs": [
            "lastNotNull"
          ]
        },
        "graphMode": "area",
        "justifyMode": "auto",
        "orientation": "horizontal",
        "reduceOptions": {
          "calcs": [
            "last"
          ],
          "fields": "",
          "values": false
        },
        "textMode": "auto"
      },
      "pluginVersion": "7.3.1",
      "targets": [
        {
          "expr": "count(gitlab_ci_environment_information{available=\"false\", project=~\"($OWNER).*\",project=~\"$PROJECT\", environment=~\"$ENVIRONMENT\"}) or vector(0)",
          "format": "time_series",
          "instant": false,
          "interval": "",
          "intervalFactor": 1,
          "legendFormat": "",
          "refId": "A"
        }
      ],
      "timeFrom": null,
      "timeShift": null,
      "title": "UNAVAILABLE",
      "type": "stat"
    },
    {
      "cacheTimeout": null,
      "datasource": null,
      "fieldConfig": {
        "defaults": {
          "custom": {},
          "decimals": 2,
          "mappings": [
            {
              "id": 0,
              "op": "=",
              "text": "N/A",
              "type": 1,
              "value": "null"
            }
          ],
          "nullValueMode": "connected",
          "thresholds": {
            "mode": "absolute",
            "steps": [
              {
                "color": "#299c46",
                "value": null
              },
              {
                "color": "rgba(237, 129, 40, 0.89)",
                "value": 600
              },
              {
                "color": "#d44a3a",
                "value": 900
              }
            ]
          },
          "unit": "none"
        },
        "overrides": []
      },
      "gridPos": {
        "h": 3,
        "w": 5,
        "x": 19,
        "y": 3
      },
      "id": 106,
      "interval": null,
      "links": [],
      "maxDataPoints": 100,
      "options": {
        "colorMode": "background",
        "fieldOptions": {
          "calcs": [
            "lastNotNull"
          ]
        },
        "graphMode": "area",
        "justifyMode": "auto",
        "orientation": "horizontal",
        "reduceOptions": {
          "calcs": [
            "lastNotNull"
          ],
          "fields": "",
          "values": false
        },
        "textMode": "auto"
      },
      "pluginVersion": "7.3.1",
      "targets": [
        {
          "expr": "avg(gitlab_ci_environment_behind_commits_count{project=~\"($OWNER).*\",project=~\"$PROJECT\", environment=~\"$ENVIRONMENT\"})",
          "format": "time_series",
          "instant": false,
          "interval": "",
          "intervalFactor": 1,
          "legendFormat": "",
          "refId": "A"
        }
      ],
      "timeFrom": null,
      "timeShift": null,
      "title": "Average environment deployment lag commits count",
      "type": "stat"
    },
    {
      "aliasColors": {},
      "bars": true,
      "dashLength": 10,
      "dashes": false,
      "datasource": null,
      "description": "",
      "fieldConfig": {
        "defaults": {
          "custom": {},
          "mappings": [],
          "thresholds": {
            "mode": "absolute",
            "steps": [
              {
                "color": "green",
                "value": null
              },
              {
                "color": "red",
                "value": 80
              }
            ]
          }
        },
        "overrides": []
      },
      "fill": 1,
      "fillGradient": 0,
      "gridPos": {
        "h": 4,
        "w": 16,
        "x": 0,
        "y": 5
      },
      "hiddenSeries": false,
      "id": 115,
      "legend": {
        "alignAsTable": true,
        "avg": false,
        "current": false,
        "hideZero": true,
        "max": false,
        "min": false,
        "rightSide": true,
        "show": true,
        "total": false,
        "values": false
      },
      "lines": false,
      "linewidth": 1,
      "nullPointMode": "null as zero",
      "options": {
        "alertThreshold": false
      },
      "percentage": false,
      "pluginVersion": "7.3.1",
      "pointradius": 2,
      "points": false,
      "renderer": "flot",
      "seriesOverrides": [],
      "spaceLength": 10,
      "stack": true,
      "steppedLine": false,
      "targets": [
        {
          "expr": "sum(increase(gitlab_ci_environment_deployment_count{project=~\"($OWNER).*\",project=~\"$PROJECT\",environment=~\"$ENVIRONMENT\"}[1m])) by (project, environment) / sum(increase(gitlab_ci_environment_deployment_count{project=~\"($OWNER).*\",project=~\"$PROJECT\",environment=~\"$ENVIRONMENT\"}[1m])) by (project, environment)",
          "format": "time_series",
          "instant": false,
          "interval": "",
          "legendFormat": "{{ environment }} - {{ project }}",
          "refId": "A"
        }
      ],
      "thresholds": [],
      "timeFrom": null,
      "timeRegions": [],
      "timeShift": null,
      "title": "DEPLOYMENTS",
      "tooltip": {
        "shared": true,
        "sort": 0,
        "value_type": "individual"
      },
      "type": "graph",
      "xaxis": {
        "buckets": null,
        "mode": "time",
        "name": null,
        "show": true,
        "values": []
      },
      "yaxes": [
        {
          "format": "short",
          "label": null,
          "logBase": 1,
          "max": null,
          "min": "0",
          "show": true
        },
        {
          "format": "short",
          "label": null,
          "logBase": 1,
          "max": null,
          "min": null,
          "show": true
        }
      ],
      "yaxis": {
        "align": false,
        "alignLevel": null
      }
    },
    {
      "cacheTimeout": null,
      "datasource": null,
      "fieldConfig": {
        "defaults": {
          "custom": {},
          "decimals": 0,
          "mappings": [
            {
              "id": 0,
              "op": "=",
              "text": "N/A",
              "type": 1,
              "value": "null"
            }
          ],
          "nullValueMode": "connected",
          "thresholds": {
            "mode": "absolute",
            "steps": [
              {
                "color": "semi-dark-blue",
                "value": null
              },
              {
                "color": "#d44a3a"
              }
            ]
          },
          "unit": "none"
        },
        "overrides": []
      },
      "gridPos": {
        "h": 3,
        "w": 3,
        "x": 16,
        "y": 6
      },
      "id": 116,
      "interval": null,
      "links": [],
      "maxDataPoints": 100,
      "options": {
        "colorMode": "background",
        "fieldOptions": {
          "calcs": [
            "lastNotNull"
          ]
        },
        "graphMode": "area",
        "justifyMode": "auto",
        "orientation": "horizontal",
        "reduceOptions": {
          "calcs": [
            "last"
          ],
          "fields": "",
          "values": false
        },
        "textMode": "auto"
      },
      "pluginVersion": "7.3.1",
      "targets": [
        {
          "expr": "sum(increase(gitlab_ci_environment_deployment_count{project=~\"($OWNER).*\",project=~\"$PROJECT\", environment=~\"$ENVIRONMENT\"}[1h]))",
          "format": "time_series",
          "instant": false,
          "interval": "",
          "intervalFactor": 1,
          "legendFormat": "",
          "refId": "A"
        }
      ],
      "timeFrom": null,
      "timeShift": null,
      "title": "DEPLOYMENTS # (in the last hour)",
      "type": "stat"
    },
    {
      "cacheTimeout": null,
      "datasource": null,
      "fieldConfig": {
        "defaults": {
          "custom": {},
          "decimals": 0,
          "mappings": [
            {
              "id": 0,
              "op": "=",
              "text": "N/A",
              "type": 1,
              "value": "null"
            }
          ],
          "nullValueMode": "connected",
          "thresholds": {
            "mode": "absolute",
            "steps": [
              {
                "color": "#299c46",
                "value": null
              },
              {
                "color": "rgba(237, 129, 40, 0.89)",
                "value": 518400
              },
              {
                "color": "#C4162A",
                "value": 1555200
              }
            ]
          },
          "unit": "dtdurations"
        },
        "overrides": []
      },
      "gridPos": {
        "h": 3,
        "w": 5,
        "x": 19,
        "y": 6
      },
      "id": 108,
      "interval": null,
      "links": [],
      "maxDataPoints": 100,
      "options": {
        "colorMode": "background",
        "fieldOptions": {
          "calcs": [
            "lastNotNull"
          ]
        },
        "graphMode": "area",
        "justifyMode": "center",
        "orientation": "horizontal",
        "reduceOptions": {
          "calcs": [
            "lastNotNull"
          ],
          "fields": "/^Value$/",
          "values": false
        },
        "textMode": "auto"
      },
      "pluginVersion": "7.3.1",
      "targets": [
        {
          "expr": "avg(gitlab_ci_environment_behind_duration_seconds{project=~\"($OWNER).*\",project=~\"$PROJECT\", environment=~\"$ENVIRONMENT\"})",
          "format": "time_series",
          "interval": "",
          "intervalFactor": 1,
          "legendFormat": "",
          "refId": "A"
        }
      ],
      "timeFrom": null,
      "timeShift": null,
      "title": "Average environment deployment lag duration",
      "type": "stat"
    },
    {
      "datasource": null,
      "fieldConfig": {
        "defaults": {
          "color": {
            "mode": "thresholds"
          },
          "custom": {
            "align": "center",
            "displayMode": "auto",
            "filterable": false
          },
          "links": [],
          "mappings": [
            {
              "from": "",
              "id": 1,
              "text": "",
              "to": "",
              "type": 1
            }
          ],
          "thresholds": {
            "mode": "absolute",
            "steps": [
              {
                "color": "green",
                "value": null
              }
            ]
          }
        },
        "overrides": [
          {
            "matcher": {
              "id": "byName",
              "options": "Environment ID"
            },
            "properties": [
              {
                "id": "links",
                "value": [
                  {
                    "targetBlank": true,
                    "title": "View environment #${__value.text}",
                    "url": "https://${GITLAB_HOST}/${__data.fields.project:raw}/-/environments/${__value.text}"
                  }
                ]
              },
              {
                "id": "custom.displayMode",
                "value": "color-background"
              },
              {
                "id": "color",
                "value": {
                  "fixedColor": "dark-blue",
                  "mode": "fixed"
                }
              },
              {
                "id": "custom.width",
                "value": 122
              }
            ]
          },
          {
            "matcher": {
              "id": "byName",
              "options": "Status"
            },
            "properties": [
              {
                "id": "custom.displayMode",
                "value": "color-background"
              },
              {
                "id": "color",
                "value": {
                  "mode": "thresholds"
                }
              },
              {
                "id": "mappings",
                "value": [
                  {
                    "from": "",
                    "id": 1,
                    "text": "RUNNING",
                    "to": "",
                    "type": 1,
                    "value": "2"
                  },
                  {
                    "from": "",
                    "id": 2,
                    "text": "FAILED",
                    "to": "",
                    "type": 1,
                    "value": "3"
                  },
                  {
                    "from": "",
                    "id": 3,
                    "text": "CANCELED",
                    "to": "",
                    "type": 1,
                    "value": "4"
                  },
                  {
                    "from": "",
                    "id": 4,
                    "text": "SKIPPED",
                    "to": "",
                    "type": 1,
                    "value": "5"
                  },
                  {
                    "from": "",
                    "id": 5,
                    "text": "PENDING",
                    "to": "",
                    "type": 1,
                    "value": "6"
                  },
                  {
                    "from": "",
                    "id": 11,
                    "text": "SUCCESS",
                    "to": "",
                    "type": 1,
                    "value": "1"
                  }
                ]
              },
              {
                "id": "thresholds",
                "value": {
                  "mode": "absolute",
                  "steps": [
                    {
                      "color": "green",
                      "value": null
                    },
                    {
                      "color": "light-blue",
                      "value": 2
                    },
                    {
                      "color": "semi-dark-red",
                      "value": 5
                    },
                    {
                      "color": "rgb(135, 135, 134)",
                      "value": 6
                    }
                  ]
                }
              }
            ]
          },
          {
            "matcher": {
              "id": "byName",
              "options": "Job"
            },
            "properties": [
              {
                "id": "custom.align",
                "value": "left"
              },
              {
                "id": "custom.width",
                "value": 230
              }
            ]
          },
          {
            "matcher": {
              "id": "byName",
              "options": "Project"
            },
            "properties": [
              {
                "id": "custom.align",
                "value": "left"
              },
              {
                "id": "custom.width",
                "value": 218
              }
            ]
          },
          {
            "matcher": {
              "id": "byName",
              "options": "Ref Kind"
            },
            "properties": [
              {
                "id": "custom.width",
                "value": 98
              }
            ]
          },
          {
            "matcher": {
              "id": "byName",
              "options": "Ref Name"
            },
            "properties": [
              {
                "id": "custom.width",
                "value": 122
              }
            ]
          },
          {
            "matcher": {
              "id": "byName",
              "options": "Duration"
            },
            "properties": [
              {
                "id": "unit",
                "value": "dtdurations"
              },
              {
                "id": "thresholds",
                "value": {
                  "mode": "absolute",
                  "steps": [
                    {
                      "color": "green",
                      "value": null
                    },
                    {
                      "color": "light-orange",
                      "value": 900
                    },
                    {
                      "color": "semi-dark-red",
                      "value": 1200
                    }
                  ]
                }
              },
              {
                "id": "custom.displayMode",
                "value": "color-background"
              }
            ]
          },
          {
            "matcher": {
              "id": "byName",
              "options": "Date"
            },
            "properties": [
              {
                "id": "unit",
                "value": "dtdurations"
              },
              {
                "id": "custom.displayMode",
                "value": "color-background"
              }
            ]
          },
          {
            "matcher": {
              "id": "byName",
              "options": "Environment Name"
            },
            "properties": [
              {
                "id": "custom.width",
                "value": 218
              },
              {
                "id": "custom.align",
                "value": "left"
              }
            ]
          },
          {
            "matcher": {
              "id": "byName",
              "options": "Latest deployment"
            },
            "properties": [
              {
                "id": "links",
                "value": [
                  {
                    "targetBlank": true,
                    "title": "View job #${__value.numeric}",
                    "url": "https://${GITLAB_HOST}/${__data.fields.project:raw}/-/jobs/${__value.numeric}"
                  }
                ]
              },
              {
                "id": "custom.displayMode",
                "value": "color-background"
              },
              {
                "id": "color",
                "value": {
                  "fixedColor": "blue",
                  "mode": "fixed"
                }
              }
            ]
          },
          {
            "matcher": {
              "id": "byName",
              "options": "# of commits behind"
            },
            "properties": [
              {
                "id": "custom.displayMode",
                "value": "color-background"
              },
              {
                "id": "thresholds",
                "value": {
                  "mode": "absolute",
                  "steps": [
                    {
                      "color": "green",
                      "value": null
                    },
                    {
                      "color": "orange",
                      "value": 1
                    },
                    {
                      "color": "semi-dark-red",
                      "value": 4
                    }
                  ]
                }
              }
            ]
          },
          {
            "matcher": {
              "id": "byName",
              "options": "Time behind"
            },
            "properties": [
              {
                "id": "unit",
                "value": "dtdurations"
              },
              {
                "id": "custom.displayMode",
                "value": "color-background"
              },
              {
                "id": "thresholds",
                "value": {
                  "mode": "absolute",
                  "steps": [
                    {
                      "color": "green",
                      "value": null
                    },
                    {
                      "color": "orange",
                      "value": 1
                    },
                    {
                      "color": "semi-dark-red",
                      "value": 86400
                    }
                  ]
                }
              },
              {
                "id": "custom.width",
                "value": 278
              }
            ]
          },
          {
            "matcher": {
              "id": "byRegexp",
              "options": ".*commit$"
            },
            "properties": [
              {
                "id": "links",
                "value": [
                  {
                    "targetBlank": true,
                    "title": "View commit ${__value.text} details",
                    "url": "https://${GITLAB_HOST}/${__data.fields.Project:raw}/-/commit/${__value.text}"
                  }
                ]
              },
              {
                "id": "unit",
                "value": "string"
              }
            ]
          },
          {
            "matcher": {
              "id": "byRegexp",
              "options": ".*behind$"
            },
            "properties": [
              {
                "id": "links",
                "value": [
                  {
                    "targetBlank": true,
                    "title": "Compare commits on GitLab",
                    "url": "https://${GITLAB_HOST}/${__data.fields.Project:raw}/-/compare/${__data.fields[\"Deployed commit\"]}...${__data.fields[\"Latest commit\"]}"
                  }
                ]
              }
            ]
          }
        ]
      },
      "gridPos": {
        "h": 23,
        "w": 24,
        "x": 0,
        "y": 9
      },
      "id": 120,
      "links": [],
      "options": {
        "showHeader": true,
        "sortBy": [
          {
            "desc": true,
            "displayName": "Date"
          }
        ]
      },
      "pluginVersion": "7.3.1",
      "targets": [
        {
          "expr": "(max(gitlab_ci_environment_deployment_status{project=~\"($OWNER).*\",project=~\"$PROJECT\", environment=~\"$ENVIRONMENT\", status=~\"success\"}) by (project, environment) * 1) > 0 or\n(max(gitlab_ci_environment_deployment_status{project=~\"($OWNER).*\",project=~\"$PROJECT\", environment=~\"$ENVIRONMENT\", status=~\"running\"}) by (project, environment) * 2) > 0 or\n(max(gitlab_ci_environment_deployment_status{project=~\"($OWNER).*\",project=~\"$PROJECT\", environment=~\"$ENVIRONMENT\", status=~\"failed\"}) by (project, environment) * 3) > 0 or\n(max(gitlab_ci_environment_deployment_status{project=~\"($OWNER).*\",project=~\"$PROJECT\", environment=~\"$ENVIRONMENT\", status=~\"canceled\"}) by (project, environment) * 4) > 0 or\n(max(gitlab_ci_environment_deployment_status{project=~\"($OWNER).*\",project=~\"$PROJECT\", environment=~\"$ENVIRONMENT\", status=~\"skipped\"}) by (project, environment) * 5) > 0 or\n(max(gitlab_ci_environment_deployment_status{project=~\"($OWNER).*\",project=~\"$PROJECT\", environment=~\"$ENVIRONMENT\", status=~\"created|waiting_for_resource|preparing|pending|manual|scheduled\"}) by (project, environment) * 6) > 0",
          "format": "table",
          "hide": false,
          "instant": true,
          "interval": "",
          "intervalFactor": 1,
          "legendFormat": "",
          "refId": "A"
        },
        {
          "expr": "-max(time() - gitlab_ci_environment_deployment_timestamp{project=~\"($OWNER).*\",project=~\"$PROJECT\", environment=~\"$ENVIRONMENT\"}) by (project, environment)",
          "format": "table",
          "hide": false,
          "instant": true,
          "interval": "",
          "intervalFactor": 1,
          "legendFormat": "",
          "refId": "B"
        },
        {
          "expr": "max(gitlab_ci_environment_deployment_duration_seconds{project=~\"($OWNER).*\",project=~\"$PROJECT\", environment=~\"$ENVIRONMENT\"}) by (project, environment)",
          "format": "table",
          "hide": false,
          "instant": true,
          "interval": "",
          "intervalFactor": 1,
          "legendFormat": "",
          "refId": "C"
        },
        {
          "expr": "max(gitlab_ci_environment_information{project=~\"($OWNER).*\",project=~\"$PROJECT\", environment=~\"$ENVIRONMENT\"}) by (environment_id, project, environment, author_email, current_commit_short_id, ref, latest_commit_short_id)",
          "format": "table",
          "instant": true,
          "interval": "",
          "legendFormat": "",
          "refId": "D"
        },
        {
          "expr": "max(gitlab_ci_environment_behind_commits_count{project=~\"($OWNER).*\",project=~\"$PROJECT\", environment=~\"$ENVIRONMENT\"}) by (project, environment)",
          "format": "table",
          "instant": true,
          "interval": "",
          "legendFormat": "",
          "refId": "E"
        },
        {
          "expr": "max(gitlab_ci_environment_behind_duration_seconds{project=~\"($OWNER).*\",project=~\"$PROJECT\", environment=~\"$ENVIRONMENT\"}) by (project, environment)",
          "format": "table",
          "instant": true,
          "interval": "",
          "legendFormat": "",
          "refId": "F"
        },
        {
          "expr": "max(gitlab_ci_environment_deployment_job_id{project=~\"($OWNER).*\",project=~\"$PROJECT\", environment=~\"$ENVIRONMENT\"}) by (project, environment)",
          "format": "table",
          "instant": true,
          "interval": "",
          "legendFormat": "",
          "refId": "G"
        }
      ],
      "timeFrom": null,
      "timeShift": null,
      "title": "ENVIRONMENTS",
      "transformations": [
        {
          "id": "merge",
          "options": {}
        },
        {
          "id": "organize",
          "options": {
            "excludeByName": {
              "Time": true,
              "Value #A": false,
              "Value #D": true,
              "job_name": false
            },
            "indexByName": {
              "Time": 0,
              "Value #A": 15,
              "Value #B": 7,
              "Value #C": 8,
              "Value #D": 5,
              "Value #E": 12,
              "Value #F": 13,
              "Value #G": 4,
              "username": 9,
              "current_commit_short_id": 10,
              "environment": 2,
              "environment_id": 1,
              "latest_commit_short_id": 11,
              "project": 3,
              "ref": 6,
              "status": 14
            },
            "renameByName": {
              "Value #A": "Status",
              "Value #B": "Date",
              "Value #C": "Duration",
              "Value #D": "",
              "Value #E": "# of commits behind",
              "Value #F": "Time behind",
              "Value #G": "Latest deployment",
              "username": "Author",
              "current_commit_short_id": "Deployed commit",
              "environment": "Environment Name",
              "environment_id": "Environment ID",
              "job_name": "Job",
              "kind": "Ref Kind",
              "latest_commit_short_id": "Latest commit",
              "project": "Project",
              "ref": "Ref Name",
              "status": "Status"
            }
          }
        }
      ],
      "type": "table"
    }
  ],
  "refresh": "10s",
  "schemaVersion": 26,
  "style": "dark",
  "tags": [],
  "templating": {
    "list": [
      {
        "current": {
          "selected": false,
          "text": "gitlab.com",
          "value": "gitlab.com"
        },
        "error": null,
        "hide": 2,
        "label": null,
        "name": "GITLAB_HOST",
        "options": [
          {
            "selected": true,
            "text": "gitlab.com",
            "value": "gitlab.com"
          }
        ],
        "query": "gitlab.com",
        "skipUrlSync": false,
        "type": "constant"
      },
      {
        "allValue": "",
        "current": {
          "selected": true,
          "text": [
            "All"
          ],
          "value": [
            "$__all"
          ]
        },
        "datasource": "prometheus",
        "definition": "label_values(gitlab_ci_environment_information, project)",
        "error": null,
        "hide": 0,
        "includeAll": true,
        "label": "owner",
        "multi": true,
        "name": "OWNER",
        "options": [],
        "query": "label_values(gitlab_ci_environment_information, project)",
        "refresh": 2,
        "regex": "/(.*)\\/.*$/",
        "skipUrlSync": false,
        "sort": 1,
        "tagValuesQuery": "",
        "tags": [],
        "tagsQuery": "",
        "type": "query",
        "useTags": false
      },
      {
        "allValue": ".*",
        "current": {
          "selected": true,
          "text": [
            "All"
          ],
          "value": [
            "$__all"
          ]
        },
        "datasource": "prometheus",
        "definition": "label_values(gitlab_ci_environment_information{project=~\"($OWNER).*\"}, project)",
        "error": null,
        "hide": 0,
        "includeAll": true,
        "label": "project",
        "multi": true,
        "name": "PROJECT",
        "options": [],
        "query": "label_values(gitlab_ci_environment_information{project=~\"($OWNER).*\"}, project)",
        "refresh": 2,
        "regex": "",
        "skipUrlSync": false,
        "sort": 1,
        "tagValuesQuery": "",
        "tags": [],
        "tagsQuery": "",
        "type": "query",
        "useTags": false
      },
      {
        "allValue": ".*",
        "current": {
          "selected": true,
          "text": [
            "All"
          ],
          "value": [
            "$__all"
          ]
        },
        "datasource": "prometheus",
        "definition": "label_values(gitlab_ci_environment_information{project=~\"($OWNER).*\",project=~\"$PROJECT\"}, environment)",
        "error": null,
        "hide": 0,
        "includeAll": true,
        "label": "environment",
        "multi": true,
        "name": "ENVIRONMENT",
        "options": [],
        "query": "label_values(gitlab_ci_environment_information{project=~\"($OWNER).*\",project=~\"$PROJECT\"}, environment)",
        "refresh": 2,
        "regex": "",
        "skipUrlSync": false,
        "sort": 1,
        "tagValuesQuery": "",
        "tags": [],
        "tagsQuery": "",
        "type": "query",
        "useTags": false
      }
    ]
  },
  "time": {
    "from": "now-1h",
    "to": "now"
  },
  "timepicker": {
    "refresh_intervals": [
      "10s",
      "30s",
      "1m",
      "5m",
      "15m",
      "30m",
      "1h",
      "2h",
      "1d"
    ],
    "time_options": [
      "5m",
      "15m",
      "1h",
      "6h",
      "12h",
      "24h",
      "2d",
      "7d",
      "30d"
    ]
  },
  "timezone": "",
  "title": "GitLab CI environments & deployments",
  "uid": "gitlab_ci_environment_deployments",
  "version": 2
}
